sabhi_utils/__init__.py
sabhi_utils/ccv.py
sabhi_utils/ccv_split.py
sabhi_utils/dict_utils.py
sabhi_utils/face_utility.py
sabhi_utils/kmeans_utils.py
sabhi_utils/pytorch_utils.py
sabhi_utils/text_utils.py
sabhi_utils/utility.py
sabhi_utils/image_utils/__init__.py
sabhi_utils/image_utils/corner_detector.py
sabhi_utils/image_utils/detectors.py
sabhi_utils/image_utils/global_features.py
sabhi_utils/image_utils/hough_line_corner_detector.py
sabhi_utils/image_utils/local_features.py
sabhi_utils/image_utils/processors.py
sabhi_utils/image_utils/template_matching.py
sabhi_utils/image_utils/utils.py
sabhi_utils-2.0.8.dist-info/METADATA
sabhi_utils-2.0.8.dist-info/WHEEL
sabhi_utils-2.0.8.dist-info/top_level.txt
sabhi_utils-2.0.8.dist-info/RECORD
